whoarder/__init__.py
whoarder/clippings.py
whoarder/test/__init__.py
whoarder-0.3.2.data/scripts/whoarder
whoarder-0.3.2.dist-info/LICENSE
whoarder-0.3.2.dist-info/METADATA
whoarder-0.3.2.dist-info/WHEEL
whoarder-0.3.2.dist-info/top_level.txt
whoarder-0.3.2.dist-info/zip-safe
whoarder-0.3.2.dist-info/RECORD
