Metadata-Version: 2.1
Name: whoarder
Version: 0.3.2
Summary: whoarder converts your Kindle's 'My Clippings.txt' file to a more pleasant, sortable, filterable HTML file
Home-page: https://github.com/ronjouch/whoarder
Author: Ronan Jouchet
Author-email: ronan@jouchet.fr
License: LICENSE.txt
Keywords: amazon kindle transform notes highlights clippings html
Platform: UNKNOWN
Classifier: Development Status :: 3 - Alpha
Classifier: Environment :: Console
Classifier: Intended Audience :: End Users/Desktop
Classifier: License :: OSI Approved :: BSD License
Classifier: Operating System :: OS Independent
Classifier: Programming Language :: Python
Classifier: Programming Language :: Python :: 3
Classifier: Programming Language :: Python :: 3.3
Classifier: Topic :: Text Processing
Classifier: Topic :: Utilities
License-File: LICENSE
Requires-Dist: jinja2
Requires-Dist: chardet2
